trace_event_handler/__init__.py
trace_event_handler/trace_event_handler.py
trace_event_handler-0.0.4.dist-info/LICENSE
trace_event_handler-0.0.4.dist-info/METADATA
trace_event_handler-0.0.4.dist-info/WHEEL
trace_event_handler-0.0.4.dist-info/top_level.txt
trace_event_handler-0.0.4.dist-info/RECORD
