Metadata-Version: 2.1
Name: trace-event-handler
Version: 0.0.4
Summary: Python Logging Handler which dumps in the Trace Event Format supported by Chromium based browsers.
Home-page: https://github.com/lochbrunner/trace_event_handler
Author: Matthias Lochbrunner
Author-email: matthias_lochbrunner@web.de
License: UNKNOWN
Platform: UNKNOWN
Classifier: Programming Language :: Python :: 3
Classifier: License :: OSI Approved :: MIT License
Classifier: Operating System :: OS Independent
Requires-Python: >=3.6
